.gitignore
.travis.yml
LICENSE
README.rst
setup.py
bin/rhcephcompose
rhcephcompose/__init__.py
rhcephcompose/artifacts.py
rhcephcompose/build.py
rhcephcompose/common_koji.py
rhcephcompose/compose.py
rhcephcompose/comps.py
rhcephcompose/log.py
rhcephcompose/main.py
rhcephcompose/variants.py
rhcephcompose.egg-info/PKG-INFO
rhcephcompose.egg-info/SOURCES.txt
rhcephcompose.egg-info/dependency_links.txt
rhcephcompose.egg-info/not-zip-safe
rhcephcompose.egg-info/pbr.json
rhcephcompose.egg-info/requires.txt
rhcephcompose.egg-info/top_level.txt
rhcephcompose/gather/__init__.py
rhcephcompose/gather/chacra.py
rhcephcompose/gather/koji.py
rhcephcompose/metadata/__init__.py
rhcephcompose/metadata/composeinfo.py
rhcephcompose/metadata/debs.py
rhcephcompose/tests/conftest.py
rhcephcompose/tests/test_artifacts.py
rhcephcompose/tests/test_build.py
rhcephcompose/tests/test_compose.py
rhcephcompose/tests/test_comps.py
rhcephcompose/tests/test_main.py
rhcephcompose/tests/test_variants.py
rhcephcompose/tests/fixtures/basic.conf
rhcephcompose/tests/fixtures/builds-ceph-2.0-trusty.txt
rhcephcompose/tests/fixtures/builds-ceph-2.0-xenial.txt
rhcephcompose/tests/fixtures/comps-basic.xml
rhcephcompose/tests/fixtures/variants-basic.xml
rhcephcompose/tests/fixtures/extra_files/EULA
rhcephcompose/tests/fixtures/extra_files/GPL
rhcephcompose/tests/fixtures/extra_files/README