Metadata-Version: 1.0
Name: rhcephcompose
Version: 1.4.1
Summary: Distribution compose tool
Home-page: UNKNOWN
Author: Ken Dreyer
Author-email: kdreyer@redhat.com
License: MIT
Keywords: compose,pungi
Platform: UNKNOWN
